src/__about__.py
src/__init__.py
src/main.py
dbt_to_junit-0.2.0.dist-info/METADATA
dbt_to_junit-0.2.0.dist-info/WHEEL
dbt_to_junit-0.2.0.dist-info/entry_points.txt
dbt_to_junit-0.2.0.dist-info/licenses/LICENSE
dbt_to_junit-0.2.0.dist-info/RECORD
