Metadata-Version: 2.4
Name: dbt-to-junit
Version: 0.2.0
Summary: Convert dbt's target/run_results.json into a JUnit XML report so Azure DevOps (ADO) can display dbt test results in the Tests tab.
Project-URL: Documentation, https://github.com/jorgecontrerasostos/dbt-junit-xml#readme
Project-URL: Issues, https://github.com/jorgecontrerasostos/dbt-junit-xml/issues
Project-URL: Source, https://github.com/jorgecontrerasostos/dbt-junit-xml
Author-email: Jorge Contreras <jorgecontrerasostos@gmail.com>
License-File: LICENSE
Classifier: Development Status :: 4 - Beta
Classifier: Programming Language :: Python
Classifier: Programming Language :: Python :: 3.8
Classifier: Programming Language :: Python :: 3.9
Classifier: Programming Language :: Python :: 3.10
Classifier: Programming Language :: Python :: 3.11
Classifier: Programming Language :: Python :: 3.12
Classifier: Programming Language :: Python :: Implementation :: CPython
Classifier: Programming Language :: Python :: Implementation :: PyPy
Requires-Python: >=3.8
Requires-Dist: junit-xml>=1.9
Provides-Extra: dev
Requires-Dist: black>=24.8.0; extra == 'dev'
Requires-Dist: pytest; extra == 'dev'
Requires-Dist: pytest-cov; extra == 'dev'
Requires-Dist: ruff; extra == 'dev'
